dallsporpoise/__init__.py
dallsporpoise/_version.py
dallsporpoise-0.0.2.dev3.data/scripts/motcorrect_vector.py
dallsporpoise-0.0.2.dev3.data/scripts/vec2mat.py
dallsporpoise-0.0.2.dev3.dist-info/LICENSE.txt
dallsporpoise-0.0.2.dev3.dist-info/METADATA
dallsporpoise-0.0.2.dev3.dist-info/WHEEL
dallsporpoise-0.0.2.dev3.dist-info/dependency_links.txt
dallsporpoise-0.0.2.dev3.dist-info/top_level.txt
dallsporpoise-0.0.2.dev3.dist-info/RECORD
